stack_alert/__init__.py
stack_alert/api.py
stack_alert/cli.py
stack_alert/templates/email_template.html.jinja
stack_alert-0.2.1.dist-info/entry_points.txt
stack_alert-0.2.1.dist-info/LICENSE.txt
stack_alert-0.2.1.dist-info/WHEEL
stack_alert-0.2.1.dist-info/METADATA
stack_alert-0.2.1.dist-info/RECORD
