Metadata-Version: 2.1
Name: stack_alert
Version: 0.2.1
Summary: Be notified when interesting questions are posted to Stack Exchange sites.
Home-page: https://github.com/kalekundert/stack_alert
Author: Kale Kundert
Author-email: kale@thekunderts.net
Requires-Python: ~=3.6
Classifier: Programming Language :: Python :: 3
Classifier: License :: OSI Approved :: GNU General Public License v3 (GPLv3)
Requires-Dist: appdirs
Requires-Dist: docopt
Requires-Dist: excerpt-html
Requires-Dist: inform
Requires-Dist: jinja2
Requires-Dist: more_itertools
Requires-Dist: requests
Requires-Dist: toml
Requires-Dist: tqdm
Requires-Dist: sphinx ; extra == "docs"
Requires-Dist: sphinx_rtd_theme ; extra == "docs"
Requires-Dist: autoclasstoc ; extra == "docs"
Requires-Dist: pytest ; extra == "tests"
Requires-Dist: pytest-cov ; extra == "tests"
Requires-Dist: coveralls ; extra == "tests"
Project-URL: Bug Tracker, https://github.com/kalekundert/stack_alert/issues
Project-URL: Continuous Integration, https://github.com/kalekundert/stack_alert/actions
Project-URL: Documentation, https://stack_alert.readthedocs.io/en/latest/
Project-URL: Test Coverage, https://coveralls.io/github/kalekundert/stack_alert
Project-URL: Version Control, https://github.com/kalekundert/stack_alert
Provides-Extra: docs
Provides-Extra: tests
